roundr/__init__.py
roundr/roundr.py
roundr-1.2.dist-info/LICENCE
roundr-1.2.dist-info/METADATA
roundr-1.2.dist-info/WHEEL
roundr-1.2.dist-info/top_level.txt
roundr-1.2.dist-info/RECORD
