Metadata-Version: 2.1
Name: roundr
Version: 1.2
Summary: Round Number
Home-page: https://github.com/RezaAbbaszadeh80/roundr
Author: Reza Abbaszadeh
Author-email: rezaabbaszadehlinkedin@gmail.com
Classifier: Programming Language :: Python :: 3
License-File: LICENCE
